logpose
