Metadata-Version: 1.1
Name: logpose
Version: 0.0.1a7
Summary: A python log library
Home-page: https://github.com/saleepeppe/logpose
Author: Giuseppe Savino
Author-email: giuseppe.savino@outlook.com
License: UNKNOWN
Keywords: development logging
Platform: UNKNOWN
Classifier: Development Status :: 3 - Alpha
Classifier: Intended Audience :: Developers
Classifier: Topic :: Software Development :: Version Control
Classifier: License :: OSI Approved :: Apache Software License
Classifier: Programming Language :: Python :: 3.6
